rsdb/__init__.py
rsdb/connection.py
rsdb/orm.py
rsdb/utils.py
rsdb-0.9.2.dist-info/LICENSE
rsdb-0.9.2.dist-info/METADATA
rsdb-0.9.2.dist-info/WHEEL
rsdb-0.9.2.dist-info/top_level.txt
rsdb-0.9.2.dist-info/RECORD
